web_automation/__init__.py
web_automation/exceptions.py
web_automation/framework.py
web_automation-1.0.1.dist-info/LICENSE
web_automation-1.0.1.dist-info/METADATA
web_automation-1.0.1.dist-info/WHEEL
web_automation-1.0.1.dist-info/top_level.txt
web_automation-1.0.1.dist-info/RECORD
