Metadata-Version: 2.1
Name: web-automation
Version: 1.0.1
Summary: Framework built on top of Selenium framework for easy setup and config
Author-email: The Bored Genius <th3b0redgenius@gmail.com>
License: MIT License
Project-URL: Homepage, https://github.com/theboredgenius/web-automation
Keywords: automation,web,framework
Classifier: Programming Language :: Python :: 3
Classifier: License :: OSI Approved :: MIT License
Classifier: Operating System :: OS Independent
Requires-Python: >=3.7
License-File: LICENSE
Requires-Dist: selenium (==4.7.2)
